spotify_random_saved_album/__init__.py
spotify_random_saved_album/spotify_random_saved_album.py
spotify_random_saved_album/resources/__init__.py
spotify_random_saved_album-0.0.8.dist-info/LICENCE
spotify_random_saved_album-0.0.8.dist-info/METADATA
spotify_random_saved_album-0.0.8.dist-info/WHEEL
spotify_random_saved_album-0.0.8.dist-info/entry_points.txt
spotify_random_saved_album-0.0.8.dist-info/top_level.txt
spotify_random_saved_album-0.0.8.dist-info/RECORD
