Metadata-Version: 2.1
Name: spotify-random-saved-album
Version: 0.0.8
Summary: Get an URL to a random saved Spotify album.
Author: Matej Ciglenečki
License: MIT License        
Project-URL: Homepage, https://github.com/ciglenecki/spotify-random-saved-album
Requires-Python: >=3.7
License-File: LICENCE
Requires-Dist: spotipy
